yocho/__init__.py
yocho/pyld_xtl/__init__.py
yocho/pyld_xtl/cli.py
yocho.pyld_xtl-0.2.0a4.dist-info/entry_points.txt
yocho.pyld_xtl-0.2.0a4.dist-info/WHEEL
yocho.pyld_xtl-0.2.0a4.dist-info/METADATA
yocho.pyld_xtl-0.2.0a4.dist-info/RECORD
