Metadata-Version: 2.1
Name: yocho.pyld-xtl
Version: 0.2.0a4
Summary: Extra tools for pyld
Home-page: https://gitlab.com/aucampia/wip/pyld-xtl
License: CC0-1.0
Author: Iwan Aucamp
Author-email: aucampia@gmail.com
Requires-Python: >=3.6,<4.0
Classifier: License :: CC0 1.0 Universal (CC0 1.0) Public Domain Dedication
Classifier: Programming Language :: Python :: 3
Classifier: Programming Language :: Python :: 3.6
Classifier: Programming Language :: Python :: 3.7
Classifier: Programming Language :: Python :: 3.8
Requires-Dist: pyld (>=2.0.3,<3.0.0)
Requires-Dist: pyyaml (>=5.3.1,<6.0.0)
Requires-Dist: requests (>=2.24.0,<3.0.0)
